amvka/__init__.py
amvka/__main__.py
amvka/cli.py
amvka/config.py
amvka/conversation.py
amvka/environment.py
amvka/executor.py
amvka/langchain_llm.py
amvka/llm.py
amvka/utils.py
amvka-2.0.0.dist-info/licenses/LICENSE
amvka-2.0.0.dist-info/METADATA
amvka-2.0.0.dist-info/WHEEL
amvka-2.0.0.dist-info/entry_points.txt
amvka-2.0.0.dist-info/top_level.txt
amvka-2.0.0.dist-info/RECORD
