Metadata-Version: 2.4
Name: amvka
Version: 2.0.0
Summary: AMVKA 2.0 - Universal AI Assistant with 100+ providers via LangChain. Commands + Conversations in one intelligent tool.
Author-email: Lalit Sangore <lgsangore2002@gmail.com>
Maintainer-email: Lalit Sangore <lgsangore2002@gmail.com>
License: MIT
Project-URL: Homepage, https://github.com/lalitt08/amvka-ai-assistant-terminal
Project-URL: Repository, https://github.com/lalitt08/amvka-ai-assistant-terminal
Project-URL: Issues, https://github.com/lalitt08/amvka-ai-assistant-terminal/issues
Project-URL: Documentation, https://github.com/lalitt08/amvka-ai-assistant-terminal/blob/main/README.md
Project-URL: Changelog, https://github.com/lalitt08/amvka-ai-assistant-terminal/blob/main/CHANGELOG.md
Keywords: cli,ai,langchain,openai,gemini,claude,groq,natural-language,shell,command,automation,assistant,chatbot,devops,terminal
Classifier: Development Status :: 5 - Production/Stable
Classifier: Intended Audience :: Developers
Classifier: Intended Audience :: System Administrators
Classifier: Intended Audience :: End Users/Desktop
Classifier: License :: OSI Approved :: MIT License
Classifier: Operating System :: OS Independent
Classifier: Operating System :: Microsoft :: Windows
Classifier: Operating System :: POSIX :: Linux
Classifier: Operating System :: MacOS
Classifier: Programming Language :: Python :: 3
Classifier: Programming Language :: Python :: 3.8
Classifier: Programming Language :: Python :: 3.9
Classifier: Programming Language :: Python :: 3.10
Classifier: Programming Language :: Python :: 3.11
Classifier: Programming Language :: Python :: 3.12
Classifier: Topic :: System :: Shells
Classifier: Topic :: Utilities
Classifier: Topic :: Software Development :: User Interfaces
Classifier: Topic :: Scientific/Engineering :: Artificial Intelligence
Classifier: Topic :: Communications :: Chat
Classifier: Environment :: Console
Requires-Python: >=3.8
License-File: LICENSE
Requires-Dist: langchain>=0.1.0
Requires-Dist: langchain-community>=0.0.10
Requires-Dist: requests>=2.31.0
Requires-Dist: click>=8.0.0
Requires-Dist: colorama>=0.4.0
Provides-Extra: dev
Requires-Dist: pytest>=6.0; extra == "dev"
Requires-Dist: pytest-cov>=2.0; extra == "dev"
Requires-Dist: black>=21.0; extra == "dev"
Requires-Dist: flake8>=3.8; extra == "dev"
Requires-Dist: mypy>=0.910; extra == "dev"
Requires-Dist: build>=0.7.0; extra == "dev"
Requires-Dist: twine>=3.0.0; extra == "dev"
Provides-Extra: openai
Requires-Dist: langchain-openai>=0.0.5; extra == "openai"
Provides-Extra: gemini
Requires-Dist: langchain-google-genai>=0.0.5; extra == "gemini"
Provides-Extra: claude
Requires-Dist: langchain-anthropic>=0.0.5; extra == "claude"
Provides-Extra: groq
Requires-Dist: langchain-groq>=0.1.0; extra == "groq"
Provides-Extra: cohere
Requires-Dist: langchain-cohere>=0.0.5; extra == "cohere"
Provides-Extra: azure
Requires-Dist: langchain-openai>=0.0.5; extra == "azure"
Provides-Extra: aws
Requires-Dist: langchain-aws>=0.0.5; extra == "aws"
Provides-Extra: ollama
Requires-Dist: langchain-community>=0.0.10; extra == "ollama"
Provides-Extra: huggingface
Requires-Dist: langchain-huggingface>=0.0.3; extra == "huggingface"
Provides-Extra: popular
Requires-Dist: langchain-openai>=0.0.5; extra == "popular"
Requires-Dist: langchain-google-genai>=0.0.5; extra == "popular"
Requires-Dist: langchain-anthropic>=0.0.5; extra == "popular"
Requires-Dist: langchain-groq>=0.1.0; extra == "popular"
Provides-Extra: fast
Requires-Dist: langchain-groq>=0.1.0; extra == "fast"
Requires-Dist: langchain-google-genai>=0.0.5; extra == "fast"
Provides-Extra: enterprise
Requires-Dist: langchain-openai>=0.0.5; extra == "enterprise"
Requires-Dist: langchain-aws>=0.0.5; extra == "enterprise"
Requires-Dist: langchain-anthropic>=0.0.5; extra == "enterprise"
Provides-Extra: local
Requires-Dist: langchain-community>=0.0.10; extra == "local"
Provides-Extra: all-providers
Requires-Dist: langchain-openai>=0.0.5; extra == "all-providers"
Requires-Dist: langchain-google-genai>=0.0.5; extra == "all-providers"
Requires-Dist: langchain-anthropic>=0.0.5; extra == "all-providers"
Requires-Dist: langchain-groq>=0.1.0; extra == "all-providers"
Requires-Dist: langchain-cohere>=0.0.5; extra == "all-providers"
Requires-Dist: langchain-aws>=0.0.5; extra == "all-providers"
Requires-Dist: langchain-huggingface>=0.0.3; extra == "all-providers"
Requires-Dist: langchain-community>=0.0.10; extra == "all-providers"
Dynamic: license-file
